swarmauri_tool_searchword/SearchWordTool.py
swarmauri_tool_searchword/__init__.py
swarmauri_tool_searchword-0.1.1.dist-info/LICENSE
swarmauri_tool_searchword-0.1.1.dist-info/METADATA
swarmauri_tool_searchword-0.1.1.dist-info/WHEEL
swarmauri_tool_searchword-0.1.1.dist-info/RECORD
