Metadata-Version: 2.3
Name: swarmauri_tool_searchword
Version: 0.1.1
Summary: A tool for searching a specific word or phrase in a file.
License: Apache-2.0
Keywords: search,tool,word,phrase,file,highlight,swarmauri
Author: Vijay Vignesh Prasad Rao
Author-email: vijayvigneshp02@gmail.com
Requires-Python: >=3.10,<3.13
Classifier: License :: OSI Approved :: Apache Software License
Classifier: Natural Language :: English
Classifier: Programming Language :: Python :: 3.10
Classifier: Programming Language :: Python :: 3.11
Classifier: Development Status :: 3 - Alpha
Requires-Dist: pydantic
Requires-Dist: requests
Requires-Dist: swarmauri_base
Requires-Dist: swarmauri_core
Requires-Dist: swarmauri_standard
